{"stat.useItem.minecraft.glass":26,"stat.useItem.minecraft.lapis_block":13,"stat.walkOneCm":40069,"stat.useItem.minecraft.quartz_block":73,"achievement.openInventory":10,"stat.leaveGame":17,"stat.useItem.minecraft.gold_block":4,"stat.useItem.minecraft.emerald_block":10,"stat.useItem.minecraft.stonebrick":8,"stat.useItem.minecraft.glowstone":5,"stat.flyOneCm":50197,"stat.jump":128,"stat.playOneMinute":69444,"stat.useItem.minecraft.sea_lantern":2,"stat.useItem.minecraft.wool":11,"stat.crouchOneCm":32,"stat.timeSinceDeath":69444,"stat.useItem.minecraft.dirt":3,"stat.sprintOneCm":17774,"stat.useItem.minecraft.diamond_block":2,"achievement.exploreAllBiomes":{"value":0,"progress":["Beach","River","Plains","Taiga","Deep Ocean"]}}